{"pornstars":{"0":{"0":"Abby Lee Brazil","1":"5n_abby-lee-brazil"},"1":{"0":"Adrian Maya","1":"1qq_adrian-maya"},"2":{"0":"Alex Tanner","1":"ni_alex-tanner"},"3":{"0":"Alia Starr","1":"2is_alia-starr"},"4":{"0":"Amai Liu","1":"5d_amai-liu"},"5":{"0":"Apolonia Lapiedra","1":"5z3_apolonia-lapiedra"},"6":{"0":"Babaloo Monique","1":"gn_babaloo-monique"},"7":{"0":"Bella Danger","1":"sc_bella-danger"},"8":{"0":"Breanne Benson","1":"7h_breanne-benson"},"9":{"0":"Brianna Love","1":"an_brianna-love"},"10":{"0":"Caroline Pierce","1":"56_caroline-pierce"},"11":{"0":"Charley Chase","1":"b8_charley-chase"},"12":{"0":"Charlotte Stokely","1":"fm_charlotte-stokely"},"13":{"0":"Claudia Marie","1":"7y_claudia-marie"},"14":{"0":"Daisy Marie","1":"f4_daisy-marie"},"15":{"0":"Dee Siren","1":"1qd_dee-siren"},"16":{"0":"Destiny Dixon","1":"e0_destiny-dixon"},"17":{"0":"Emily Addison","1":"cd_emily-addison"},"18":{"0":"Emily Bloom","1":"sm_emily-bloom"},"19":{"0":"Emma Starr","1":"6o_emma-starr"},"20":{"0":"Frida Sante","1":"2zy_frida-sante"},"21":{"0":"Gina Valentino","1":"1sa_gina-valentino"},"22":{"0":"Harlow Harrison","1":"43r_harlow-harrison"},"23":{"0":"Isis Taylor","1":"6a_isis-taylor"},"24":{"0":"Jaclyn Taylor","1":"1p6_jaclyn-taylor"},"25":{"0":"Jade Jantzen","1":"1mr_jade-jantzen"},"26":{"0":"Jenna Sativa","1":"2yi_jenna-sativa"},"27":{"0":"Jessica Jaymes","1":"4n_jessica-jaymes"},"28":{"0":"Jessie Andrews","1":"l7_jessie-andrews"},"29":{"0":"Joslyn James","1":"b7_joslyn-james"},"30":{"0":"Ka Lee","1":"3q4_ka-lee"},"31":{"0":"Kapri Styles","1":"8y_kapri-styles"},"32":{"0":"Kayla Kleevage","1":"hc_kayla-kleevage"},"33":{"0":"Kaylani Lei","1":"1me_kaylani-lei"},"34":{"0":"Kennedy Leigh","1":"5y_kennedy-leigh"},"35":{"0":"Kiki Minaj","1":"fx_kiki-minaj"},"36":{"0":"Lacey Duvalle","1":"6b_lacey-duvalle"},"37":{"0":"Lexi Amor","1":"tb_lexi-amor"},"38":{"0":"London Andrews","1":"1qi_london-andrews"},"39":{"0":"Lorena Aquino","1":"7b_lorena-aquino"},"40":{"0":"Madison Scott","1":"7o_madison-scott"},"41":{"0":"Malena Morgan","1":"62_malena-morgan"},"42":{"0":"Marina Shiraishi","1":"3vl_marina-shiraishi"},"43":{"0":"Mason Moore","1":"52_mason-moore"},"44":{"0":"Mika Tan","1":"hs_mika-tan"},"45":{"0":"Mischa Brooks","1":"7l_mischa-brooks"},"46":{"0":"Nicky Ferrari","1":"46_nicky-ferrari"},"47":{"0":"Nina Rotti","1":"dk_nina-rotti"},"48":{"0":"Olivia O&#39;lovely","1":"em_olivia-o-lovely"},"49":{"0":"Randy Moore","1":"1rp_randy-moore"},"50":{"0":"Rei Mizuna","1":"6t3_rei-mizuna"},"51":{"0":"Rio Hamasaki","1":"kw_rio-hamasaki"},"52":{"0":"Sally D&#39;angelo","1":"2ch_sally-d-angelo"},"53":{"0":"Sandra Romain","1":"be_sandra-romain"},"54":{"0":"Sara Stone","1":"gr_sara-stone"},"55":{"0":"Shawna Lenee","1":"cv_shawna-lenee"},"56":{"0":"Sheena Shaw","1":"8r_sheena-shaw"},"57":{"0":"Sofia Nix","1":"7g_sofia-nix"},"58":{"0":"Vanessa Blake","1":"1zd_vanessa-blake"},"59":{"0":"Velicity Von","1":"6z_velicity-von"}}, "pagination": { "0": { "0": 9, "1": 10, "2": 11 }, "current": 8 }}