{"pornstars":{"0":{"0":"Aline","1":"29p_aline"},"1":{"0":"Alyssa Reece","1":"tf_alyssa-reece"},"2":{"0":"Amber Chase","1":"yr_amber-chase"},"3":{"0":"Andy San Dimas","1":"205_andy-san-dimas"},"4":{"0":"Angelica Heart","1":"l6_angelica-heart"},"5":{"0":"Angie","1":"6zc_angie"},"6":{"0":"Aria Giovanni","1":"u3_aria-giovanni"},"7":{"0":"Arwen Gold","1":"21p_arwen-gold"},"8":{"0":"Ayu Sakurai","1":"3hc_ayu-sakurai"},"9":{"0":"Ayumu Sena","1":"63n_ayumu-sena"},"10":{"0":"Bailey Blue","1":"1ny_bailey-blue"},"11":{"0":"Blue Angel","1":"nq_blue-angel"},"12":{"0":"Brenda James","1":"mp_brenda-james"},"13":{"0":"Briella Bounce","1":"qg_briella-bounce"},"14":{"0":"Candle Boxxx","1":"5nw_candle-boxxx"},"15":{"0":"Chanel Staxxx","1":"t0_chanel-staxxx"},"16":{"0":"Charlie Laine","1":"2hv_charlie-laine"},"17":{"0":"Christy Canyon","1":"ti_christy-canyon"},"18":{"0":"Edyn Blair","1":"4o7_edyn-blair"},"19":{"0":"Erica Lauren","1":"up_erica-lauren"},"20":{"0":"Erika Kitagawa","1":"4x8_erika-kitagawa"},"21":{"0":"Eve Laurence","1":"7n_eve-laurence"},"22":{"0":"Farrah Abraham","1":"1pp_farrah-abraham"},"23":{"0":"Georgia Peach","1":"i0_georgia-peach"},"24":{"0":"Harley Quinn","1":"4ve_harley-quinn"},"25":{"0":"Horny Lily","1":"bh_horny-lily"},"26":{"0":"Jackie Lin","1":"2wn_jackie-lin"},"27":{"0":"Kacey Jordan","1":"n7_kacey-jordan"},"28":{"0":"Kayla Green","1":"23q_kayla-green"},"29":{"0":"Kirsten Price","1":"tk_kirsten-price"},"30":{"0":"Klaudia Kelly","1":"iq_klaudia-kelly"},"31":{"0":"Linda Sweet","1":"uc_linda-sweet"},"32":{"0":"Luana Alves","1":"e8_luana-alves"},"33":{"0":"Luna C. Kitsuen","1":"1vm_luna-c-kitsuen"},"34":{"0":"Madison Chandler","1":"e4_madison-chandler"},"35":{"0":"Makayla Cox","1":"32f_makayla-cox"},"36":{"0":"Maki Houjo","1":"2u6_maki-houjo"},"37":{"0":"Melissa Lauren","1":"h5_melissa-lauren"},"38":{"0":"Memphis Monroe","1":"6m_memphis-monroe"},"39":{"0":"Molly Bennett","1":"1m8_molly-bennett"},"40":{"0":"Monica Sexxxton","1":"24r_monica-sexxxton"},"41":{"0":"Niki Snow","1":"53o_niki-snow"},"42":{"0":"Prinzzess","1":"2hb_prinzzess"},"43":{"0":"Rei Kitajima","1":"3sl_rei-kitajima"},"44":{"0":"Rikki Sixx","1":"49_rikki-sixx"},"45":{"0":"Riko Tachibana","1":"km_riko-tachibana"},"46":{"0":"Sabrina Banks","1":"24h_sabrina-banks"},"47":{"0":"Samanta Lily","1":"6vz_samanta-lily"},"48":{"0":"Samia Duarte","1":"c5_samia-duarte"},"49":{"0":"Shane Blair","1":"5sr_shane-blair"},"50":{"0":"Sierra Sanders","1":"vq_sierra-sanders"},"51":{"0":"Skylar Green","1":"r6_skylar-green"},"52":{"0":"Stacie Lane","1":"1wi_stacie-lane"},"53":{"0":"Taylor Jones","1":"1ty_taylor-jones"},"54":{"0":"Tia Tanaka","1":"ld_tia-tanaka"},"55":{"0":"Vanessa Luna","1":"uo_vanessa-luna"},"56":{"0":"Veronica Radke","1":"ve_veronica-radke"},"57":{"0":"Victoria White","1":"2p4_victoria-white"},"58":{"0":"Violet Monroe","1":"2e6_violet-monroe"},"59":{"0":"Whitney Stevens","1":"ip_whitney-stevens"}}, "pagination": { "0": { "0": 18, "1": 19, "2": 20 }, "current": 17 }}